stylobate_mgmt/__init__.py
stylobate_mgmt/stylo.py
stylobate_mgmt-0.0.2.dist-info/LICENSE
stylobate_mgmt-0.0.2.dist-info/METADATA
stylobate_mgmt-0.0.2.dist-info/WHEEL
stylobate_mgmt-0.0.2.dist-info/entry_points.txt
stylobate_mgmt-0.0.2.dist-info/top_level.txt
stylobate_mgmt-0.0.2.dist-info/RECORD
