Metadata-Version: 2.1
Name: stylobate-mgmt
Version: 0.0.2
Summary: Manage instances of Stylobate-based projects
Home-page: http://github.com/digitaltembo/stylobate-mgmt
Author: Nolan Hawkins
Author-email: nolanhhawkins@gmail.com
License: MIT
Platform: UNKNOWN
Classifier: Programming Language :: Python :: 3
Classifier: License :: OSI Approved :: MIT License
Classifier: Operating System :: OS Independent
Requires-Python: >=3.1
